{
  "task_id": "AJF-CAI_r0_chunk3",
  "saved_at": "2026-01-01T00:13:35.713795",
  "lf_results": {
    "2026-01-11": [],
    "2026-01-10": [
      {
        "Date": "Saturday, January 10, 2026",
        "Flight": "SM322",
        "DEP": "21:15",
        "SOLD": 66,
        "FULL CAPACITY": 175,
        "LF%": 0.3771,
        "LowestAvail": "O9",
        "LASTSOLD": "2025-12-31 00:00:00",
        "WEEKLY PROGRESS": 36,
        "RBD": {
          "N": 0,
          "P": 0,
          "A": 0,
          "E": 0,
          "I": 0,
          "O": 65,
          "U": 0,
          "X": 0,
          "T": 0,
          "W": 0,
          "S": 1,
          "G": 0,
          "L": 0,
          "V": 0,
          "K": 0,
          "Q": 0,
          "H": 0,
          "M": 0,
          "B": 0,
          "Y": 0
        },
        "GRP": 0,
        "EQP": "320",
        "Brd-Off": "AJF-CAI",
        "SOLD TODAY": 0,
        "SOLD YDAY": 5,
        "CONNECTING_PASSENGERS": null
      }
    ],
    "2026-01-09": [],
    "2026-01-08": [
      {
        "Date": "Thursday, January 08, 2026",
        "Flight": "SM322",
        "DEP": "21:55",
        "SOLD": 104,
        "FULL CAPACITY": 175,
        "LF%": 0.5943,
        "LowestAvail": "X7",
        "LASTSOLD": "2025-12-31 00:00:00",
        "WEEKLY PROGRESS": 36,
        "RBD": {
          "N": 0,
          "P": 0,
          "A": 0,
          "E": 0,
          "I": 0,
          "O": 5,
          "U": 34,
          "X": 42,
          "T": 11,
          "W": 4,
          "S": 6,
          "G": 0,
          "L": 0,
          "V": 0,
          "K": 2,
          "Q": 0,
          "H": 0,
          "M": 0,
          "B": 0,
          "Y": 0
        },
        "GRP": 0,
        "EQP": "320",
        "Brd-Off": "AJF-CAI",
        "SOLD TODAY": 0,
        "SOLD YDAY": 12,
        "CONNECTING_PASSENGERS": {
          "sm_flight": "SM322",
          "sm_route": "AJF-CAI",
          "sm_dep": "2155",
          "sm_arr": "2240",
          "connecting_passengers": []
        }
      }
    ],
    "2026-01-07": [],
    "2026-01-06": [
      {
        "Date": "Tuesday, January 06, 2026",
        "Flight": "SM322",
        "DEP": "11:00",
        "SOLD": 85,
        "FULL CAPACITY": 175,
        "LF%": 0.4857,
        "LowestAvail": "X3",
        "LASTSOLD": "2025-12-31 00:00:00",
        "WEEKLY PROGRESS": 52,
        "RBD": {
          "N": 0,
          "P": 0,
          "A": 0,
          "E": 0,
          "I": 0,
          "O": 41,
          "U": 30,
          "X": 7,
          "T": 3,
          "W": 0,
          "S": 4,
          "G": 0,
          "L": 0,
          "V": 0,
          "K": 0,
          "Q": 0,
          "H": 0,
          "M": 0,
          "B": 0,
          "Y": 0
        },
        "GRP": 0,
        "EQP": "320",
        "Brd-Off": "AJF-CAI",
        "SOLD TODAY": 0,
        "SOLD YDAY": 12,
        "CONNECTING_PASSENGERS": {
          "sm_flight": "SM322",
          "sm_route": "AJF-CAI",
          "sm_dep": "1100",
          "sm_arr": "1145",
          "connecting_passengers": [
            {
              "outbound_flight": "SM0054",
              "outbound_route": "CAI-LXR",
              "outbound_dep": "1530",
              "passengers": [
                {
                  "iata": "RUHS228YD"
                },
                {
                  "iata": "RUHS228YD"
                },
                {
                  "iata": "RUHS228YD"
                }
              ]
            }
          ]
        }
      }
    ]
  },
  "lf_errors": {}
}