{
  "timestamp": "2026-01-06T07:56:30.593025",
  "service": "market-insights",
  "counters": {
    "oal_requests_total": {
      "description": "Total OAL API requests",
      "values": []
    },
    "lf_requests_total": {
      "description": "Total LF requests",
      "values": [
        {
          "labels": {
            "destination": "HBE",
            "origin": "MED",
            "status": "success"
          },
          "value": 13.0
        }
      ]
    },
    "errors_total": {
      "description": "Total errors",
      "values": []
    }
  },
  "gauges": {
    "routes_in_progress": {
      "description": "Routes currently being processed",
      "values": [
        {
          "labels": {},
          "value": 0.0
        }
      ]
    },
    "flights_analyzed": {
      "description": "Total flights analyzed in session",
      "values": [
        {
          "labels": {
            "direction": "lf"
          },
          "value": 7.0
        }
      ]
    },
    "circuit_breaker_state": {
      "description": "Circuit breaker state (0=closed, 1=open)",
      "values": []
    }
  },
  "histograms": {
    "request_duration_seconds": {
      "description": "Request duration in seconds",
      "data": {}
    },
    "route_processing_seconds": {
      "description": "Route processing duration",
      "data": {
        "{'route': 'MED-HBE'}": {
          "sum": 157.493498,
          "count": 13,
          "buckets": {
            "5.0": 6,
            "10.0": 12,
            "30.0": 12,
            "60.0": 12,
            "120.0": 13,
            "300.0": 13
          },
          "p50": 5.208333333333333,
          "p95": 7.645833333333334,
          "p99": 7.862499999999999
        }
      }
    }
  }
}