{
  "task_id": "ELQ-CAI_chunk1",
  "saved_at": "2025-12-24T18:32:57.350400",
  "lf_results": {
    "2026-01-04": [],
    "2026-01-03": [
      {
        "Date": "Saturday, January 03, 2026",
        "Flight": "SM428",
        "DEP": "00:01",
        "SOLD": 22,
        "FULL CAPACITY": 168,
        "LF%": 0.131,
        "LowestAvail": "O9",
        "LASTSOLD": "2025-12-21 00:00:00",
        "WEEKLY PROGRESS": 4,
        "RBD": {
          "N": 0,
          "P": 0,
          "A": 0,
          "E": 0,
          "I": 0,
          "O": 4,
          "U": 12,
          "X": 3,
          "T": 0,
          "W": 0,
          "S": 3,
          "G": 0,
          "L": 0,
          "V": 0,
          "K": 0,
          "Q": 0,
          "H": 0,
          "M": 0,
          "B": 0,
          "Y": 0
        },
        "GRP": 0,
        "EQP": "320",
        "Brd-Off": "ELQ-CAI",
        "SOLD TODAY": 0,
        "SOLD YDAY": 0,
        "CONNECTING_PASSENGERS": null
      }
    ],
    "2026-01-02": [],
    "2026-01-01": [
      {
        "Date": "Thursday, January 01, 2026",
        "Flight": "SM428",
        "DEP": "19:10",
        "SOLD": 34,
        "FULL CAPACITY": 168,
        "LF%": 0.2024,
        "LowestAvail": "I9",
        "LASTSOLD": "2025-12-24 00:00:00",
        "WEEKLY PROGRESS": 8,
        "RBD": {
          "N": 0,
          "P": 0,
          "A": 0,
          "E": 0,
          "I": 3,
          "O": 16,
          "U": 6,
          "X": 6,
          "T": 1,
          "W": 0,
          "S": 2,
          "G": 0,
          "L": 0,
          "V": 0,
          "K": 0,
          "Q": 0,
          "H": 0,
          "M": 0,
          "B": 0,
          "Y": 0
        },
        "GRP": 0,
        "EQP": "320",
        "Brd-Off": "ELQ-CAI",
        "SOLD TODAY": 3,
        "SOLD YDAY": 1,
        "CONNECTING_PASSENGERS": null
      }
    ],
    "2025-12-31": [],
    "2025-12-30": []
  },
  "lf_errors": {}
}