{
  "task_id": "JED-LXR_chunk1",
  "saved_at": "2025-12-24T18:32:05.161132",
  "lf_results": {
    "2026-01-04": [],
    "2026-01-03": [],
    "2026-01-02": [],
    "2026-01-01": [],
    "2025-12-31": [],
    "2025-12-30": [
      {
        "Date": "Tuesday, December 30, 2025",
        "Flight": "SM482",
        "DEP": "02:45",
        "SOLD": 180,
        "FULL CAPACITY": 168,
        "LF%": 1.0714,
        "LowestAvail": "CLOSED",
        "LASTSOLD": "2025-12-15 00:00:00",
        "WEEKLY PROGRESS": 0,
        "RBD": {
          "N": 0,
          "P": 0,
          "A": 0,
          "E": 0,
          "I": 0,
          "O": 0,
          "U": 180,
          "X": 0,
          "T": 0,
          "W": 0,
          "S": 0,
          "G": 0,
          "L": 0,
          "V": 0,
          "K": 0,
          "Q": 0,
          "H": 0,
          "M": 0,
          "B": 0,
          "Y": 0
        },
        "GRP": 180,
        "EQP": "320",
        "Brd-Off": "JED-LXR",
        "SOLD TODAY": 0,
        "SOLD YDAY": 0,
        "CONNECTING_PASSENGERS": null
      },
      {
        "Date": "Tuesday, December 30, 2025",
        "Flight": "SM984",
        "DEP": "06:40",
        "SOLD": 179,
        "FULL CAPACITY": 168,
        "LF%": 1.0655,
        "LowestAvail": "CLOSED",
        "LASTSOLD": "2025-12-15 00:00:00",
        "WEEKLY PROGRESS": 0,
        "RBD": {
          "N": 0,
          "P": 0,
          "A": 0,
          "E": 0,
          "I": 0,
          "O": 0,
          "U": 179,
          "X": 0,
          "T": 0,
          "W": 0,
          "S": 0,
          "G": 0,
          "L": 0,
          "V": 0,
          "K": 0,
          "Q": 0,
          "H": 0,
          "M": 0,
          "B": 0,
          "Y": 0
        },
        "GRP": 179,
        "EQP": "320",
        "Brd-Off": "JED-LXR",
        "SOLD TODAY": 0,
        "SOLD YDAY": 0,
        "CONNECTING_PASSENGERS": null
      },
      {
        "Date": "Tuesday, December 30, 2025",
        "Flight": "SM430",
        "DEP": "10:00",
        "SOLD": 179,
        "FULL CAPACITY": 168,
        "LF%": 1.0655,
        "LowestAvail": "CLOSED",
        "LASTSOLD": "2025-12-15 00:00:00",
        "WEEKLY PROGRESS": 0,
        "RBD": {
          "N": 0,
          "P": 0,
          "A": 0,
          "E": 0,
          "I": 0,
          "O": 0,
          "U": 179,
          "X": 0,
          "T": 0,
          "W": 0,
          "S": 0,
          "G": 0,
          "L": 0,
          "V": 0,
          "K": 0,
          "Q": 0,
          "H": 0,
          "M": 0,
          "B": 0,
          "Y": 0
        },
        "GRP": 179,
        "EQP": "320",
        "Brd-Off": "JED-LXR",
        "SOLD TODAY": 0,
        "SOLD YDAY": 0,
        "CONNECTING_PASSENGERS": null
      },
      {
        "Date": "Tuesday, December 30, 2025",
        "Flight": "SM982",
        "DEP": "17:00",
        "SOLD": 177,
        "FULL CAPACITY": 168,
        "LF%": 1.0536,
        "LowestAvail": "CLOSED",
        "LASTSOLD": "2025-12-22 00:00:00",
        "WEEKLY PROGRESS": 11,
        "RBD": {
          "N": 0,
          "P": 8,
          "A": 0,
          "E": 0,
          "I": 34,
          "O": 0,
          "U": 134,
          "X": 1,
          "T": 0,
          "W": 0,
          "S": 0,
          "G": 0,
          "L": 0,
          "V": 0,
          "K": 0,
          "Q": 0,
          "H": 0,
          "M": 0,
          "B": 0,
          "Y": 0
        },
        "GRP": 143,
        "EQP": "320",
        "Brd-Off": "JED-LXR",
        "SOLD TODAY": 0,
        "SOLD YDAY": 0,
        "CONNECTING_PASSENGERS": null
      },
      {
        "Date": "Tuesday, December 30, 2025",
        "Flight": "SM484",
        "DEP": "19:00",
        "SOLD": 179,
        "FULL CAPACITY": 168,
        "LF%": 1.0655,
        "LowestAvail": "CLOSED",
        "LASTSOLD": "2025-12-16 00:00:00",
        "WEEKLY PROGRESS": 0,
        "RBD": {
          "N": 0,
          "P": 0,
          "A": 0,
          "E": 0,
          "I": 0,
          "O": 0,
          "U": 179,
          "X": 0,
          "T": 0,
          "W": 0,
          "S": 0,
          "G": 0,
          "L": 0,
          "V": 0,
          "K": 0,
          "Q": 0,
          "H": 0,
          "M": 0,
          "B": 0,
          "Y": 0
        },
        "GRP": 179,
        "EQP": "320",
        "Brd-Off": "JED-LXR",
        "SOLD TODAY": 0,
        "SOLD YDAY": 0,
        "CONNECTING_PASSENGERS": null
      }
    ]
  },
  "lf_errors": {}
}